odoo8_addon_l10n_ch_payment_slip_base_transaction_id-8.0.1.0.0.99.dev4-py2.7-nspkg.pth
odoo8_addon_l10n_ch_payment_slip_base_transaction_id-8.0.1.0.0.99.dev4.dist-info/METADATA
odoo8_addon_l10n_ch_payment_slip_base_transaction_id-8.0.1.0.0.99.dev4.dist-info/RECORD
odoo8_addon_l10n_ch_payment_slip_base_transaction_id-8.0.1.0.0.99.dev4.dist-info/WHEEL
odoo8_addon_l10n_ch_payment_slip_base_transaction_id-8.0.1.0.0.99.dev4.dist-info/namespace_packages.txt
odoo8_addon_l10n_ch_payment_slip_base_transaction_id-8.0.1.0.0.99.dev4.dist-info/top_level.txt
odoo_addons/l10n_ch_payment_slip_base_transaction_id/README.rst
odoo_addons/l10n_ch_payment_slip_base_transaction_id/__init__.py
odoo_addons/l10n_ch_payment_slip_base_transaction_id/__openerp__.py
odoo_addons/l10n_ch_payment_slip_base_transaction_id/static/description/icon.png
